MakerToolbox/__init__.py
MakerToolbox/example.py
MakerToolbox/algorithms/Paths.py
MakerToolbox/algorithms/__init__.py
MakerToolbox/gpio/InputPin.py
MakerToolbox/gpio/OutputPin.py
MakerToolbox/gpio/PWMPin.py
MakerToolbox/gpio/RaspberryPi.py
MakerToolbox/gpio/__init__.py
MakerToolbox/hardware/Button.py
MakerToolbox/hardware/DCMotorDriver.py
MakerToolbox/hardware/ServoMotor.py
MakerToolbox/hardware/StepperDrivers.py
MakerToolbox/hardware/__init__.py
MakerToolbox/machines/CoreXY.py
MakerToolbox/machines/__init__.py
MakerToolbox/utility/DiscreteVector.py
MakerToolbox/utility/__init__.py
makertoolbox-0.0.19.dist-info/METADATA
makertoolbox-0.0.19.dist-info/WHEEL
makertoolbox-0.0.19.dist-info/licenses/LICENSE
makertoolbox-0.0.19.dist-info/RECORD
