Metadata-Version: 2.1
Name: MakerToolbox
Version: 0.0.19
Summary: The MakerToolbox module provides a collection of tools for working with various electronic hardware.
Project-URL: Homepage, https://github.com/jackcampbell19/MakerToolbox
Project-URL: Bug Tracker, https://github.com/jackcampbell19/MakerToolbox/issues
Author-email: Jack Campbell <makertoolboxrepo@gmail.com>
License-File: LICENSE
Classifier: License :: OSI Approved :: MIT License
Classifier: Operating System :: OS Independent
Classifier: Programming Language :: Python :: 3
Requires-Python: >=3.9
